blm/__init__.py
blm/backlash_model.py
blm-1.1.dist-info/LICENSE.txt
blm-1.1.dist-info/METADATA
blm-1.1.dist-info/WHEEL
blm-1.1.dist-info/top_level.txt
blm-1.1.dist-info/zip-safe
blm-1.1.dist-info/RECORD
