Metadata-Version: 2.1
Name: blm
Version: 1.1
Summary: A simple model to describe the backlash effect in physics simulations
Home-page: https://github.com/famura/blm
Author: Fabio Muratore
Author-email: fabio.muratore@famura.net
Project-URL: Source, https://github.com/famura/blm
Project-URL: Bug Reports, https://github.com/famura/blm/issues
Keywords: backlash,simulation,physics,modeling
Classifier: License :: OSI Approved :: MIT License
Classifier: Development Status :: 5 - Production/Stable
Classifier: Operating System :: OS Independent
Classifier: Programming Language :: Python :: 3.8
Classifier: Programming Language :: Python :: 3 :: Only
Requires-Python: >=3.7, <4
License-File: LICENSE.txt
Requires-Dist: numpy
Requires-Dist: tabulate
Requires-Dist: tqdm
Provides-Extra: dev
Requires-Dist: black ; extra == 'dev'
Requires-Dist: isort ; extra == 'dev'
Requires-Dist: matplotlib ; extra == 'dev'
Requires-Dist: pytest ; extra == 'dev'
Requires-Dist: pytest-cov ; extra == 'dev'
